isoxmlviz/LineStringUtil.py
isoxmlviz/Pivot.py
isoxmlviz/__init__.py
isoxmlviz/__main__.py
isoxmlviz/visualize.py
isoxmlviz/webmap.py
isoxmlviz-1.4.13.dist-info/licenses/LICENSE.txt
isoxmlviz-1.4.13.dist-info/METADATA
isoxmlviz-1.4.13.dist-info/WHEEL
isoxmlviz-1.4.13.dist-info/entry_points.txt
isoxmlviz-1.4.13.dist-info/top_level.txt
isoxmlviz-1.4.13.dist-info/RECORD
