Metadata-Version: 2.4
Name: isoxmlviz
Version: 1.4.13
Summary: A utility to show basic ISO 1178-10 XML data
Author: Kenneth Lausdahl
Author-email: kenneth@lausdahl.com
Project-URL: Bug Reports, https://github.com/lausdahl/isoxmlviz/issues
Project-URL: Funding, https://github.com/lausdahl/isoxmlviz
Project-URL: Source, https://github.com/lausdahl/isoxmlviz
Keywords: isoxml,isobus,iso-11783-10
Classifier: Development Status :: 3 - Alpha
Classifier: Intended Audience :: Developers
Classifier: Topic :: Software Development :: Build Tools
Classifier: License :: OSI Approved :: MIT License
Classifier: Programming Language :: Python :: 3
Classifier: Programming Language :: Python :: 3.6
Classifier: Programming Language :: Python :: 3.7
Classifier: Programming Language :: Python :: 3.8
Classifier: Programming Language :: Python :: 3.9
Classifier: Programming Language :: Python :: 3 :: Only
Requires-Python: >=3.8, <4
License-File: LICENSE.txt
Requires-Dist: matplotlib
Requires-Dist: pymap3d<4,>=3.0.1
Requires-Dist: shapely<3,>=2
Requires-Dist: folium
Provides-Extra: dev
Requires-Dist: check-manifest; extra == "dev"
Provides-Extra: test
Requires-Dist: coverage; extra == "test"
Dynamic: author
Dynamic: author-email
Dynamic: classifier
Dynamic: description
Dynamic: description-content-type
Dynamic: keywords
Dynamic: license-file
Dynamic: project-url
Dynamic: provides-extra
Dynamic: requires-dist
Dynamic: requires-python
Dynamic: summary
